odoo/addons/document_url/README.rst
odoo/addons/document_url/__init__.py
odoo/addons/document_url/__manifest__.py
odoo/addons/document_url/i18n/am.po
odoo/addons/document_url/i18n/ar.po
odoo/addons/document_url/i18n/bg.po
odoo/addons/document_url/i18n/bs.po
odoo/addons/document_url/i18n/ca.po
odoo/addons/document_url/i18n/cs.po
odoo/addons/document_url/i18n/da.po
odoo/addons/document_url/i18n/de.po
odoo/addons/document_url/i18n/document_url.pot
odoo/addons/document_url/i18n/el.po
odoo/addons/document_url/i18n/el_GR.po
odoo/addons/document_url/i18n/en_AU.po
odoo/addons/document_url/i18n/en_GB.po
odoo/addons/document_url/i18n/es.po
odoo/addons/document_url/i18n/es_AR.po
odoo/addons/document_url/i18n/es_CL.po
odoo/addons/document_url/i18n/es_CO.po
odoo/addons/document_url/i18n/es_CR.po
odoo/addons/document_url/i18n/es_DO.po
odoo/addons/document_url/i18n/es_EC.po
odoo/addons/document_url/i18n/es_ES.po
odoo/addons/document_url/i18n/es_MX.po
odoo/addons/document_url/i18n/es_PY.po
odoo/addons/document_url/i18n/es_VE.po
odoo/addons/document_url/i18n/et.po
odoo/addons/document_url/i18n/eu.po
odoo/addons/document_url/i18n/fa.po
odoo/addons/document_url/i18n/fi.po
odoo/addons/document_url/i18n/fr.po
odoo/addons/document_url/i18n/fr_CA.po
odoo/addons/document_url/i18n/gl.po
odoo/addons/document_url/i18n/gu.po
odoo/addons/document_url/i18n/he.po
odoo/addons/document_url/i18n/hi.po
odoo/addons/document_url/i18n/hr.po
odoo/addons/document_url/i18n/hu.po
odoo/addons/document_url/i18n/hy.po
odoo/addons/document_url/i18n/id.po
odoo/addons/document_url/i18n/is.po
odoo/addons/document_url/i18n/it.po
odoo/addons/document_url/i18n/ja.po
odoo/addons/document_url/i18n/ka.po
odoo/addons/document_url/i18n/kab.po
odoo/addons/document_url/i18n/kk.po
odoo/addons/document_url/i18n/ko.po
odoo/addons/document_url/i18n/ln.po
odoo/addons/document_url/i18n/lo.po
odoo/addons/document_url/i18n/lt.po
odoo/addons/document_url/i18n/lv.po
odoo/addons/document_url/i18n/mk.po
odoo11_addon_document_url-11.0.1.0.0.99.dev10.dist-info/METADATA
odoo11_addon_document_url-11.0.1.0.0.99.dev10.dist-info/WHEEL
odoo11_addon_document_url-11.0.1.0.0.99.dev10.dist-info/top_level.txt
odoo11_addon_document_url-11.0.1.0.0.99.dev10.dist-info/RECORD
